weave_sdk/__init__.py
weave_sdk-0.0.2.dist-info/WHEEL
weave_sdk-0.0.2.dist-info/METADATA
weave_sdk-0.0.2.dist-info/RECORD
