Metadata-Version: 2.4
Name: weave-sdk
Version: 0.0.2
Summary: Weave SDK for building applications with Weave.
Author: Aspect Analytics
Author-email: Aspect Analytics <info@aspect-analytics.com>
Classifier: Programming Language :: Python :: 3
Classifier: Operating System :: OS Independent
Requires-Python: >=3.13
Project-URL: Homepage, https://www.aspect-analytics.com/
